persons/__init__.py
persons/api_client.py
persons/configuration.py
persons/rest.py
persons/api/__init__.py
persons/api/admins_api.py
persons/api/crzp_api.py
persons/api/developers_api.py
persons/api/link_api.py
persons/api/manage2_api.py
persons/api/manage_api.py
persons/api/public_api.py
persons/api/reference_api.py
persons/models/__init__.py
persons/models/base_list_search_extension_type.py
persons/models/base_list_type.py
persons/models/birth_date_type.py
persons/models/code_value_type.py
persons/models/config_body.py
persons/models/contact_type.py
persons/models/context_type.py
persons/models/context_type_persons.py
persons/models/context_type_roles.py
persons/models/date_time_type.py
persons/models/department_type.py
persons/models/document_entry.py
persons/models/document_entry_list.py
persons/models/document_metadata_type.py
persons/models/error_model.py
persons/models/geo_point_jtsk_type.py
persons/models/geo_point_type.py
persons/models/identifier_type.py
persons/models/individual_list_type.py
persons/models/individual_type.py
persons/models/issuing_type.py
persons/models/location_type.py
persons/models/mail_address_type.py
persons/models/member_type.py
persons/models/person_link_type.py
persons/models/person_list_item.py
persons/models/person_list_type.py
persons/models/person_type.py
persons/models/person_type_type.py
persons/models/phone_number_type.py
persons/models/pid_type.py
persons/models/reference_registry.py
persons/models/role_category_type.py
persons/models/role_list_item.py
persons/models/role_list_type.py
persons/models/role_type.py
persons/models/tag_item_type.py
persons/models/tag_list_type.py
persons/models/tag_type.py
test/__init__.py
test/test_admins_api.py
test/test_base_list_search_extension_type.py
test/test_base_list_type.py
test/test_birth_date_type.py
test/test_code_value_type.py
test/test_config_body.py
test/test_contact_type.py
test/test_context_type.py
test/test_context_type_persons.py
test/test_context_type_roles.py
sysnet_persons-1.0.4.2.dist-info/LICENSE
sysnet_persons-1.0.4.2.dist-info/METADATA
sysnet_persons-1.0.4.2.dist-info/WHEEL
sysnet_persons-1.0.4.2.dist-info/top_level.txt
sysnet_persons-1.0.4.2.dist-info/RECORD
