Metadata-Version: 2.1
Name: sysnet-persons
Version: 1.0.4.2
Summary: SYSNET Persons Registry REST API client
Home-page: 
Author-email: Radim Jaeger <info@sysnet.cz>
License: Apache License
Project-URL: Homepage, https://github.com/SYSNET-CZ/swagger/tree/main/clients/persons
Classifier: Programming Language :: Python :: 3
Classifier: License :: OSI Approved :: Apache Software License
Classifier: Operating System :: OS Independent
Classifier: Topic :: Internet :: WWW/HTTP :: Dynamic Content
Requires-Python: >=3.9
License-File: LICENSE
